MANIFEST.in
README.rst
setup.py
collective/__init__.py
collective/__init__.pyc
collective.ptg.highslide.egg-info/PKG-INFO
collective.ptg.highslide.egg-info/SOURCES.txt
collective.ptg.highslide.egg-info/dependency_links.txt
collective.ptg.highslide.egg-info/entry_points.txt
collective.ptg.highslide.egg-info/namespace_packages.txt
collective.ptg.highslide.egg-info/not-zip-safe
collective.ptg.highslide.egg-info/requires.txt
collective.ptg.highslide.egg-info/top_level.txt
collective/ptg/__init__.py
collective/ptg/__init__.pyc
collective/ptg/highslide/__init__.py
collective/ptg/highslide/__init__.pyc
collective/ptg/highslide/configure.zcml
collective/ptg/highslide/highslide.pt
collective/ptg/highslide/i18n.sh
collective/ptg/highslide/locales/collective.ptg.highslide.pot
collective/ptg/highslide/locales/manual.pot
collective/ptg/highslide/locales/de/LC_MESSAGES/collective.ptg.highslide.mo
collective/ptg/highslide/locales/de/LC_MESSAGES/collective.ptg.highslide.po
collective/ptg/highslide/locales/es/LC_MESSAGES/collective.ptg.highslide.mo
collective/ptg/highslide/locales/es/LC_MESSAGES/collective.ptg.highslide.po
collective/ptg/highslide/locales/eu/LC_MESSAGES/collective.ptg.highslide.mo
collective/ptg/highslide/locales/eu/LC_MESSAGES/collective.ptg.highslide.po
collective/ptg/highslide/locales/fi/LC_MESSAGES/collective.ptg.highslide.mo
collective/ptg/highslide/locales/fi/LC_MESSAGES/collective.ptg.highslide.po
collective/ptg/highslide/locales/fr/LC_MESSAGES/collective.ptg.highslide.mo
collective/ptg/highslide/locales/fr/LC_MESSAGES/collective.ptg.highslide.po
collective/ptg/highslide/locales/it/LC_MESSAGES/collective.ptg.highslide.mo
collective/ptg/highslide/locales/it/LC_MESSAGES/collective.ptg.highslide.po
collective/ptg/highslide/locales/nl/LC_MESSAGES/collective.ptg.highslide.mo
collective/ptg/highslide/locales/nl/LC_MESSAGES/collective.ptg.highslide.po
collective/ptg/highslide/locales/no/LC_MESSAGES/collective.ptg.highslide.mo
collective/ptg/highslide/locales/no/LC_MESSAGES/collective.ptg.highslide.po
collective/ptg/highslide/locales/pt_BR/LC_MESSAGES/collective.ptg.highslide.mo
collective/ptg/highslide/locales/pt_BR/LC_MESSAGES/collective.ptg.highslide.po
collective/ptg/highslide/resources/highslide-full.js
collective/ptg/highslide/resources/highslide-full.min.js
collective/ptg/highslide/resources/highslide-full.packed.js
