Metadata-Version: 1.0
Name: collective.ptg.highslide
Version: 1.1
Summary: UNKNOWN
Home-page: https://github.com/collective/collective.ptg.highslide
Author: Nathan Van Gheem
Author-email: vangheem@gmail.com
License: GPL
Keywords: plone plonetruegallery
Platform: UNKNOWN
Classifier: Framework :: Plone
Classifier: Programming Language :: Python
